justmltools/__init__.py
justmltools/cli/__init__.py
justmltools/cli/cli_arguments_parser.py
justmltools/config/__init__.py
justmltools/config/abstract_data_path_config.py
justmltools/config/bucket_data_path_config.py
justmltools/config/gitlab_data_path_config.py
justmltools/config/local_data_path_config.py
justmltools/config/mlflow_data_path_config.py
justmltools/experiment/__init__.py
justmltools/experiment/abstract_config.py
justmltools/experiment/abstract_experiment.py
justmltools/experiment/tracker.py
justmltools/nlp/__init__.py
justmltools/nlp/word_embedder.py
justmltools/repo/__init__.py
justmltools/repo/abstract_repo_downloader.py
justmltools/repo/bucket_repo_downloader.py
justmltools/repo/gitlab_repo_downloader.py
justmltools/repo/mlflow_repo_downloader.py
justmltools/s3/__init__.py
justmltools/s3/aws_credentials.py
justmltools/s3/s3_bucket_object_downloader.py
justmltools/s3/s3_bucket_object_finder.py
justmltools/s3/s3_bucket_object_uploader.py
justmltools/s3/s3_copier.py
justmltools/s3/s3_downloader.py
justmltools/s3/s3_uploader.py
justmltools/s3/s3_url.py
justmltools-4.0.0.dist-info/LICENSE
justmltools-4.0.0.dist-info/METADATA
justmltools-4.0.0.dist-info/WHEEL
justmltools-4.0.0.dist-info/top_level.txt
justmltools-4.0.0.dist-info/RECORD
