Metadata-Version: 2.1
Name: justmltools
Version: 4.0.0
Summary: A library for recurring tasks in machine learning projects
Home-page: https://github.com/BigNerd/justmltools
Author: Matthias Burbach
Author-email: matthias.burbach@web.de
Classifier: Programming Language :: Python :: 3
Classifier: License :: OSI Approved :: MIT License
Classifier: Operating System :: OS Independent
Requires-Python: >=3.7
License-File: LICENSE
Requires-Dist: boto3
Requires-Dist: inflection
Requires-Dist: mlflow <3.0.0
Requires-Dist: requests
Requires-Dist: six
